{
    "manifest": {
        "publishingInformation": {
            "locales": {
                "en-US": {
                    "name": "Github Statistics",
                    "summary": "Sample Short Description",
                    "description": "Sample Full Description",
                    "examplePhrases": [
                        "Alexa what are my github stats"
                    ],
                    "keywords": []
                }
            },
            "isAvailableWorldwide": true,
            "testingInstructions": "Sample Testing Instructions",
            "distributionCountries": []
        },
        "apis": {
            "custom": {
                "endpoint": {
                    "sourceDir": "lambda/custom",
                    "uri": "ask-gs"
                }
            }
        },
        "manifestVersion": "1.0"
    }
}
